pinecone_plugin_interface/__init__.py
pinecone_plugin_interface/actions/__init__.py
pinecone_plugin_interface/actions/constants.py
pinecone_plugin_interface/actions/discover_namespace_packages.py
pinecone_plugin_interface/actions/discover_plugins.py
pinecone_plugin_interface/actions/installation.py
pinecone_plugin_interface/actions/load_and_install.py
pinecone_plugin_interface/logging.py
pinecone_plugin_interface/pinecone_plugin.py
pinecone_plugin_interface/plugin_metadata.py
pinecone_plugin_interface-0.0.6.dist-info/METADATA
pinecone_plugin_interface-0.0.6.dist-info/WHEEL
pinecone_plugin_interface-0.0.6.dist-info/RECORD
